.DS_Store
sample/__init__.py
scholarNetwork/__init__.py
scholarNetwork/scholarNetwork.py
scholarNetwork-1.2.2.3.dist-info/DESCRIPTION.rst
scholarNetwork-1.2.2.3.dist-info/METADATA
scholarNetwork-1.2.2.3.dist-info/RECORD
scholarNetwork-1.2.2.3.dist-info/WHEEL
scholarNetwork-1.2.2.3.dist-info/entry_points.txt
scholarNetwork-1.2.2.3.dist-info/metadata.json
scholarNetwork-1.2.2.3.dist-info/top_level.txt
