Metadata-Version: 2.0
Name: scholarNetwork
Version: 1.2.2.3
Summary: Coauthor-Network of your Google Scholar
Home-page: https://github.com/chengjun/scholarNetwork
Author: Cheng-Jun Wang & Lingfei Wu
Author-email: wangchj04@gmail.com; wwlf850927@gmail.com
License: MIT
Keywords: Google Scholar
Platform: UNKNOWN
Classifier: Development Status :: 3 - Alpha
Classifier: Intended Audience :: Developers
Classifier: Topic :: Software Development :: Build Tools
Classifier: License :: OSI Approved :: MIT License
Classifier: Programming Language :: Python :: 2
Classifier: Programming Language :: Python :: 2.6
Classifier: Programming Language :: Python :: 2.7
Classifier: Programming Language :: Python :: 3
Classifier: Programming Language :: Python :: 3.2
Classifier: Programming Language :: Python :: 3.3
Classifier: Programming Language :: Python :: 3.4
Provides-Extra: dev
Requires-Dist: check-manifest; extra == 'dev'
Provides-Extra: test
Requires-Dist: beautifulsoup4; extra == 'test'
Requires-Dist: coverage; extra == 'test'
Requires-Dist: matplotlib; extra == 'test'
Requires-Dist: networkx; extra == 'test'
